chams/__init__.py
chams/__main__.py
chams/utils.py
chams-0.2.0.dist-info/entry_points.txt
chams-0.2.0.dist-info/WHEEL
chams-0.2.0.dist-info/METADATA
chams-0.2.0.dist-info/RECORD
